dserver_dependency_graph_plugin/__init__.py
dserver_dependency_graph_plugin/config.py
dserver_dependency_graph_plugin/graph.py
dserver_dependency_graph_plugin/schemas.py
dserver_dependency_graph_plugin/version.py
dserver_dependency_graph_plugin-0.4.2.dist-info/licenses/LICENSE
dserver_dependency_graph_plugin-0.4.2.dist-info/METADATA
dserver_dependency_graph_plugin-0.4.2.dist-info/WHEEL
dserver_dependency_graph_plugin-0.4.2.dist-info/entry_points.txt
dserver_dependency_graph_plugin-0.4.2.dist-info/top_level.txt
dserver_dependency_graph_plugin-0.4.2.dist-info/RECORD
