Metadata-Version: 2.4
Name: dserver-dependency-graph-plugin
Version: 0.4.2
Summary: dserver plugin for receiving s3 notifications on updated objects.
Author-email: "Johannes L. Hörmann" <johannes.laurin@gmail.com>
License: MIT License
Project-URL: Documentation, https://github.com/livMatS/dserver-dependency-graph-plugin/blob/main/README.rst
Project-URL: Repository, https://github.com/livMatS/dserver-dependency-graph-plugin
Project-URL: Changelog, https://github.com/livMatS/dserver-dependency-graph-plugin/blob/main/CHANGELOG.rst
License-File: LICENSE
Requires-Dist: dtoolcore>=3.18.0
Requires-Dist: dservercore>=0.20.0
Requires-Dist: dserver-direct-mongo-plugin
Provides-Extra: test
Requires-Dist: dservercore; extra == "test"
Requires-Dist: dserver-retrieve-plugin-mongo; extra == "test"
Requires-Dist: dserver-search-plugin-mongo; extra == "test"
Requires-Dist: pytest; extra == "test"
Requires-Dist: pytest-cov; extra == "test"
Dynamic: license-file
